ddeutil/observe/__about__.py
ddeutil/observe/__init__.py
ddeutil/observe/app.py
ddeutil/observe/backend.py
ddeutil/observe/conf.py
ddeutil/observe/crud.py
ddeutil/observe/db.py
ddeutil/observe/deps.py
ddeutil/observe/initial.py
ddeutil/observe/auth/__init__.py
ddeutil/observe/auth/crud.py
ddeutil/observe/auth/deps.py
ddeutil/observe/auth/routes.py
ddeutil/observe/auth/securities.py
ddeutil/observe/auth/views.py
ddeutil/observe/auth/models/__init__.py
ddeutil/observe/auth/models/policy.py
ddeutil/observe/auth/models/ratelimit.py
ddeutil/observe/auth/models/token.py
ddeutil/observe/auth/models/user.py
ddeutil/observe/auth/schemas/__init__.py
ddeutil/observe/auth/schemas/role.py
ddeutil/observe/auth/schemas/token.py
ddeutil/observe/auth/schemas/user.py
ddeutil/observe/auth/schemas/userview.py
ddeutil/observe/routes/__init__.py
ddeutil/observe/routes/models.py
ddeutil/observe/routes/audit/__init__.py
ddeutil/observe/routes/audit/crud.py
ddeutil/observe/routes/audit/routes.py
ddeutil/observe/routes/audit/schemas.py
ddeutil/observe/routes/audit/views.py
ddeutil/observe/routes/notifications/__init__.py
ddeutil/observe/routes/notifications/routes.py
ddeutil/observe/routes/notifications/schemas.py
ddeutil/observe/routes/notifications/service.py
ddeutil/observe/routes/notifications/views.py
ddeutil/observe/routes/profile/__init__.py
ddeutil/observe/routes/profile/views.py
ddeutil/observe/routes/trace/__init__.py
ddeutil/observe/routes/trace/crud.py
ddeutil/observe/routes/trace/routes.py
ddeutil/observe/routes/trace/schemas.py
ddeutil/observe/routes/trace/views.py
ddeutil/observe/routes/workflow/__init__.py
ddeutil/observe/routes/workflow/crud.py
ddeutil/observe/routes/workflow/routes.py
ddeutil/observe/routes/workflow/schemas.py
ddeutil/observe/routes/workflow/views.py
ddeutil_observe-0.0.8.dist-info/licenses/LICENSE
ddeutil_observe-0.0.8.dist-info/METADATA
ddeutil_observe-0.0.8.dist-info/WHEEL
ddeutil_observe-0.0.8.dist-info/top_level.txt
ddeutil_observe-0.0.8.dist-info/RECORD
