Metadata-Version: 2.4
Name: ddeutil-observe
Version: 0.0.8
Summary: Lightweight observation web application
Author-email: ddeutils <korawich.anu@gmail.com>
License: MIT
Project-URL: Homepage, https://github.com/ddeutils/ddeutil-observe/
Project-URL: Source Code, https://github.com/ddeutils/ddeutil-observe/
Keywords: data,observe,utility,webserver,fastapi
Classifier: Topic :: Utilities
Classifier: Natural Language :: English
Classifier: Development Status :: 4 - Beta
Classifier: Intended Audience :: Developers
Classifier: Operating System :: OS Independent
Classifier: Programming Language :: Python
Classifier: Programming Language :: Python :: 3 :: Only
Classifier: Programming Language :: Python :: 3.9
Classifier: Programming Language :: Python :: 3.10
Classifier: Programming Language :: Python :: 3.11
Classifier: Programming Language :: Python :: 3.12
Classifier: Programming Language :: Python :: 3.13
Requires-Python: >=3.9.13
License-File: LICENSE
Requires-Dist: ddeutil[all]<0.5.0,>=0.4.10
Requires-Dist: ddeutil-workflow>=0.0.78
Requires-Dist: python-dotenv==1.1.0
Requires-Dist: fastapi==0.115.12
Requires-Dist: uvicorn==0.34.3
Requires-Dist: jinja2==3.1.6
Requires-Dist: sqlalchemy==2.0.41
Requires-Dist: greenlet==3.2.3
Requires-Dist: python-multipart==0.0.20
Requires-Dist: email-validator==2.2.0
Requires-Dist: pyjwt==2.10.1
Requires-Dist: bcrypt==4.3.0
Provides-Extra: perf
Requires-Dist: httptools; extra == "perf"
Requires-Dist: uvloop; extra == "perf"
Provides-Extra: test
Requires-Dist: httpx==0.28.1; extra == "test"
Requires-Dist: aiosqlite==0.21.0; extra == "test"
Requires-Dist: pytest-asyncio==0.26.0; extra == "test"
Dynamic: license-file
